ao3scraper/__init__.py
ao3scraper/__main__.py
ao3scraper/cli.py
ao3scraper/constants.py
ao3scraper/construct_list.py
ao3scraper/database.py
ao3scraper/file_validator.py
ao3scraper/tests/__init__.py
ao3scraper-1.0.3.dist-info/LICENSE
ao3scraper-1.0.3.dist-info/METADATA
ao3scraper-1.0.3.dist-info/WHEEL
ao3scraper-1.0.3.dist-info/entry_points.txt
ao3scraper-1.0.3.dist-info/RECORD
