Metadata-Version: 2.1
Name: ao3scraper
Version: 1.0.3
Summary: ao3scraper is a python webscraper that scrapes AO3 for fanfiction data, stores it in a database, and highlights entries when they are updated.
Home-page: https://github.com/EthanLeitch/ao3scraper
License: GPL-3.0-or-later
Author: Ethan
Author-email: ethanjohnleitch@gmail.com
Requires-Python: >=3.10,<4.0
Classifier: License :: OSI Approved :: GNU General Public License v3 or later (GPLv3+)
Classifier: Programming Language :: Python :: 3
Classifier: Programming Language :: Python :: 3.10
Classifier: Programming Language :: Python :: 3.11
Classifier: Programming Language :: Python :: 3.12
Classifier: Programming Language :: Python :: 3.13
Requires-Dist: Pygments (==2.15.0)
Requires-Dist: SQLAlchemy (>=1.4.41,<2.0.0)
Requires-Dist: alembic (>=1.8.1,<2.0.0)
Requires-Dist: ao3-api (>=2.3.0,<3.0.0)
Requires-Dist: beautifulsoup4 (==4.11.1)
Requires-Dist: certifi (==2024.07.04)
Requires-Dist: chardet (==4.0.0)
Requires-Dist: click (==8.0.1)
Requires-Dist: commonmark (==0.9.1)
Requires-Dist: configparser (>=5.3.0,<6.0.0)
Requires-Dist: deepdiff[murmur] (>=5.8.1,<6.0.0)
Requires-Dist: dictdiffer (>=0.9.0,<0.10.0)
Requires-Dist: idna (==2.10)
Requires-Dist: marshmallow-sqlalchemy (>=0.28.1,<0.29.0)
Requires-Dist: pathlib (>=1.0.1,<2.0.0)
Requires-Dist: platformdirs (>=2.5.4,<3.0.0)
Requires-Dist: pyyaml (>=6.0.2,<7.0.0)
Requires-Dist: requests (==2.32.2)
Requires-Dist: rich (==12.4.1)
Requires-Dist: ruamel-yaml (>=0.17.21,<0.18.0)
Requires-Dist: soupsieve (==2.3.2.post1)
Requires-Dist: urllib3 (==1.26.19)
Project-URL: Repository, https://github.com/EthanLeitch/ao3scraper
